xinghe-0.0.0.dist-info/METADATA
xinghe-0.0.0.dist-info/WHEEL
xinghe-0.0.0.dist-info/entry_points.txt
xinghe/__init__.py
xinghe-0.0.0.dist-info/RECORD
